local_qwen3b_part009/__init__.py
local_qwen3b_part009/qwen2.5-3b-instruct-q5_k_m.gguf.part_009
local_qwen3b_part009-0.0.1.dist-info/METADATA
local_qwen3b_part009-0.0.1.dist-info/WHEEL
local_qwen3b_part009-0.0.1.dist-info/top_level.txt
local_qwen3b_part009-0.0.1.dist-info/RECORD
