Metadata-Version: 2.4
Name: local_qwen3b_part009
Version: 0.0.1
Summary: Part 009 of qwen2.5-3b-instruct-q5_k_m.gguf
Requires-Python: >=3.9
